SvgTranslate/__init__.py
SvgTranslate/text_utils.py
SvgTranslate/workflows.py
SvgTranslate/extraction/__init__.py
SvgTranslate/extraction/extractor.py
SvgTranslate/injection/__init__.py
SvgTranslate/injection/batch.py
SvgTranslate/injection/injector.py
SvgTranslate/injection/preparation.py
svgtranslate-0.1.0.dist-info/METADATA
svgtranslate-0.1.0.dist-info/WHEEL
svgtranslate-0.1.0.dist-info/RECORD
