Metadata-Version: 2.4
Name: SvgTranslate
Version: 0.1.0
Summary: Utilities for extracting and applying translations to multilingual SVG files.
Project-URL: Homepage, https://github.com/MrIbrahem/SvgTranslate
Project-URL: Repository, https://github.com/MrIbrahem/SvgTranslate
Project-URL: Issues, https://github.com/MrIbrahem/SvgTranslate/issues
Author: Ibrahim Qasim
License: MIT
Requires-Python: >=3.10
Requires-Dist: lxml>=4.9
